simulate_argument_binding.py
simulate_argument_binding-0.1.0a0.dist-info/licenses/LICENSE
simulate_argument_binding-0.1.0a0.dist-info/METADATA
simulate_argument_binding-0.1.0a0.dist-info/WHEEL
simulate_argument_binding-0.1.0a0.dist-info/top_level.txt
simulate_argument_binding-0.1.0a0.dist-info/RECORD
