Metadata-Version: 2.4
Name: simulate-argument-binding
Version: 0.1.0a0
Summary: A pure Python library to simulate Python's internal argument binding given function signature details, default values, and user-provided arguments/keywords.
Author-email: Jifeng Wu <jifengwu2k@gmail.com>
License-Expression: MIT
Project-URL: Homepage, https://github.com/jifengwu2k/simulate-argument-binding
Project-URL: Bug Tracker, https://github.com/jifengwu2k/simulate-argument-binding/issues
Classifier: Programming Language :: Python :: 2
Classifier: Programming Language :: Python :: 3
Classifier: Operating System :: OS Independent
Requires-Python: >=2
License-File: LICENSE
Requires-Dist: typing; python_version < "3.5"
Dynamic: license-file
